syllabify/CMU_dictionary/cmudict-0.7b
syllabify/CMU_dictionary/cmudict-0.7b.phones
syllabify/CMU_dictionary/cmudict-0.7b.symbols
syllabify/__init__.py
syllabify/cli.py
syllabify/cmu_parser.py
syllabify/constants.py
syllabify/core.py
syllabify/phonemes.py
syllabify/syllables.py
syllabify/symbols.py
syllabify-0.4.1.dist-info/LICENSE
syllabify-0.4.1.dist-info/METADATA
syllabify-0.4.1.dist-info/WHEEL
syllabify-0.4.1.dist-info/entry_points.txt
syllabify-0.4.1.dist-info/RECORD
