Metadata-Version: 2.3
Name: syllabify
Version: 0.4.1
Summary: Automatically convert plain text into phonemes (US English pronunciation) and syllabify
License: MIT
Keywords: phonetics,syllabification,linguistics,cmu,pronunciation
Author: Fong-Chun Tsai
Author-email: eoleedimin@gmail.com
Requires-Python: >=3.9
Classifier: Development Status :: 3 - Alpha
Classifier: Intended Audience :: Science/Research
Classifier: Topic :: Scientific/Engineering :: Artificial Intelligence
Classifier: Topic :: Text Processing :: Linguistic
Classifier: License :: OSI Approved :: MIT License
Classifier: Programming Language :: Python :: 3
Classifier: Programming Language :: Python :: 3.9
Classifier: Programming Language :: Python :: 3.10
Classifier: Programming Language :: Python :: 3.11
Classifier: Programming Language :: Python :: 3.12
Project-URL: Homepage, https://github.com/eoleedi/syllabify
Project-URL: Repository, https://github.com/eoleedi/syllabify
